{
  "version": "1.0.0",
  "restore": {
    "projectUniqueName": "/Users/juni/Projects/DTL/DTL.MRA/DTL.MRA.MeterReads.API/DTL.MRA.MeterReads.API.csproj",
    "projectName": "DTL.MRA.MeterReads.API",
    "projectPath": "/Users/juni/Projects/DTL/DTL.MRA/DTL.MRA.MeterReads.API/DTL.MRA.MeterReads.API.csproj",
    "outputPath": "/Users/juni/Projects/DTL/DTL.MRA/DTL.MRA.MeterReads.API/obj/",
    "projectStyle": "PackageReference",
    "originalTargetFrameworks": [
      "netcoreapp2.0"
    ],
    "frameworks": {
      "netcoreapp2.0": {
        "projectReferences": {}
      }
    }
  },
  "frameworks": {
    "netcoreapp2.0": {
      "dependencies": {
        "Microsoft.NETCore.App": {
          "target": "Package",
          "version": "2.0.0"
        },
        "Microsoft.AspNetCore.All": {
          "target": "Package",
          "version": "2.0.0"
        },
        "Microsoft.EntityFrameworkCore": {
          "target": "Package",
          "version": "2.0.0"
        },
        "Microsoft.EntityFrameworkCore.Tools": {
          "target": "Package",
          "version": "2.0.0"
        },
        "Npgsql.EntityFrameworkCore.PostgreSQL": {
          "target": "Package",
          "version": "2.0.0"
        },
        "Npgsql.EntityFrameworkCore.PostgreSQL.Design": {
          "target": "Package",
          "version": "1.1.1"
        }
      },
      "imports": [
        "net461"
      ],
      "assetTargetFallback": true,
      "warn": true
    }
  }
}